{"format":1,"version":"4.5.2","settings":"aa146ad46bd9f4981b4f5541e36248e4","files":{"hunt_app___init___py":{"hash":"4911cff48f6b9e153df4c1a3ecaded19","index":{"nums":[1,0,0,0,0,0,0],"html_filename":"hunt_app___init___py.html","relative_filename":"hunt_app/__init__.py"}},"hunt_app_admin_py":{"hash":"e02307c3ffa6c6e682091b31cfe43a0b","index":{"nums":[1,6,0,6,0,0,0],"html_filename":"hunt_app_admin_py.html","relative_filename":"hunt_app/admin.py"}},"hunt_app_migrations_0001_initial_py":{"hash":"bebd8d7f1175012c58ddebb6c737ae69","index":{"nums":[1,8,0,0,0,0,0],"html_filename":"hunt_app_migrations_0001_initial_py.html","relative_filename":"hunt_app/migrations/0001_initial.py"}},"hunt_app_migrations___init___py":{"hash":"182b2dca469bf063cbcf996d517b03da","index":{"nums":[1,0,0,0,0,0,0],"html_filename":"hunt_app_migrations___init___py.html","relative_filename":"hunt_app/migrations/__init__.py"}},"hunt_app_models_py":{"hash":"8fc2b84c0e61ec3e248d45213cc37d0e","index":{"nums":[1,59,0,59,0,0,0],"html_filename":"hunt_app_models_py.html","relative_filename":"hunt_app/models.py"}},"hunt_app_permissions_py":{"hash":"9e082d5d12df6f064965bb8e8915a284","index":{"nums":[1,6,0,3,0,0,0],"html_filename":"hunt_app_permissions_py.html","relative_filename":"hunt_app/permissions.py"}},"hunt_app_serializers_py":{"hash":"8f798f33b96d75d786e03628e369a69c","index":{"nums":[1,28,0,4,0,0,0],"html_filename":"hunt_app_serializers_py.html","relative_filename":"hunt_app/serializers.py"}},"hunt_app_urls_py":{"hash":"872dc91b5cee95401aa1fcd045c32f30","index":{"nums":[1,12,0,0,0,0,0],"html_filename":"hunt_app_urls_py.html","relative_filename":"hunt_app/urls.py"}},"hunt_app_views_py":{"hash":"48651bccd4c5e7ca2e02c3ec99e2b032","index":{"nums":[1,35,0,1,0,0,0],"html_filename":"hunt_app_views_py.html","relative_filename":"hunt_app/views.py"}},"scavenger_hunt_backend___init___py":{"hash":"4911cff48f6b9e153df4c1a3ecaded19","index":{"nums":[1,0,0,0,0,0,0],"html_filename":"scavenger_hunt_backend___init___py.html","relative_filename":"scavenger_hunt_backend/__init__.py"}},"scavenger_hunt_backend_settings_py":{"hash":"c333b83c3bc9bfd008c6cabc73eeeb25","index":{"nums":[1,26,0,26,0,0,0],"html_filename":"scavenger_hunt_backend_settings_py.html","relative_filename":"scavenger_hunt_backend/settings.py"}},"scavenger_hunt_backend_urls_py":{"hash":"613c7fbf924d84829df903d76c08a0b1","index":{"nums":[1,4,0,0,0,0,0],"html_filename":"scavenger_hunt_backend_urls_py.html","relative_filename":"scavenger_hunt_backend/urls.py"}}}}